infopy/clean.py
informatica-0.0.1.dist-info/METADATA
informatica-0.0.1.dist-info/WHEEL
informatica-0.0.1.dist-info/top_level.txt
informatica-0.0.1.dist-info/RECORD
