Metadata-Version: 2.4
Name: informatica
Version: 0.0.1
Summary: Transparent data cleaning and visualization with explainable steps
Author-email: sidhulab <infopy@sidhulab.com>
License: MIT
Requires-Dist: pandas>=2.0
